Metadata-Version: 1.1
Name: collective.hello
Version: 0.2
Summary: An add-on for Plone
Home-page: http://pypi.python.org/pypi/collective.hello
Author: Simon PREVIDENTE
Author-email: simon.previdente@makina-corpus.com
License: GPL
Keywords: Python Plone
Platform: UNKNOWN
Classifier: Environment :: Web Environment
Classifier: Framework :: Plone
Classifier: Framework :: Plone :: 5.0
Classifier: Programming Language :: Python
Classifier: Programming Language :: Python :: 2.7
